ansible_directory_helper/__init__.py
ansible_directory_helper/env_directory.py
ansible_directory_helper/inventory_file.py
ansible_directory_helper/private_data.py
ansible_directory_helper-0.3.1.dist-info/METADATA
ansible_directory_helper-0.3.1.dist-info/WHEEL
ansible_directory_helper-0.3.1.dist-info/top_level.txt
ansible_directory_helper-0.3.1.dist-info/RECORD
