Metadata-Version: 2.4
Name: ansible-directory-helper
Version: 0.3.1
Summary: A small helper library to manage local directories for Ansible Runner
Author-email: "Brian St. Hilaire" <brian.st-hilaire@sanctus-tech.com>
Project-URL: Homepage, https://github.com/saint-hilaire/ansible-directory-helper
Project-URL: Issues, https://github.com/saint-hilaire/ansible-directory-helper/issues
Classifier: Development Status :: 7 - Inactive
Classifier: Environment :: Console
Classifier: Framework :: Ansible
Classifier: Programming Language :: Python :: 3
Classifier: Intended Audience :: Developers
Classifier: Intended Audience :: Information Technology
Classifier: Intended Audience :: System Administrators
Classifier: License :: OSI Approved :: Apache Software License
Requires-Python: >=3.11
Requires-Dist: pyyaml
Requires-Dist: ansible-core>=2.18
